Workbook

Sheet Dashboard
B2: Car Sales & Revenue Analysis Dashboard
B3: Period: Jan 2026 - Jul 2026 | Data source: Sales Data sheet
B5: Select Region: | C5: All
B7: Total Revenue (INR) | E7: Total Units Sold | H7: Avg Order Value (INR) | K7: Top Brand
B8: =IF($C$5="All",SUM('Sales Data'!$K$2:$K$101),SUMIFS('Sales Data'!$K$2:$K$101,'Sales Data'!$F$2:$F$101,$C$5)) -> 727952000 | E8: =IF($C$5="All",SUM('Sales Data'!$H$2:$H$101),SUMIFS('Sales Data'!$H$2:$H$101,'Sales Data'!$F$2:$F$101,$C$5)) -> 763 | H8: =IF($C$5="All",SUM('Sales Data'!$K$2:$K$101)/COUNTA('Sales Data'!$A$2:$A$101),SUMIFS('Sales Data'!$K$2:$K$101,'Sales Data'!$F$2:$F$101,$C$5)/COUNTIFS('Sales Data'!$F$2:$F$101,$C$5)) -> 7279520 | K8: =INDEX(Summary!$F$5:$F$11,MATCH(MAX(Summary!$H$5:$H$11),Summary!$H$5:$H$11,0)) -> Mahindra

Sheet Sales Data
A1: Sale ID | B1: Date | C1: Brand | D1: Model | E1: Fuel Type | F1: Region | G1: Dealer | H1: Units Sold | I1: Unit Price (INR) | J1: Discount (%) | K1: Revenue (INR)
A2: S0001 | B2: 46047 | C2: Tata | D2: Punch | E2: Electric | F2: North | G2: Prime Motors | H2: 14 | I2: 700000 | J2: 10 | K2: =H2*I2*(1-J2/100) -> 8820000
A3: S0002 | B3: 46134 | C3: Tata | D3: Tiago | E3: Petrol | F3: Central | G3: City Auto Hub | H3: 1 | I3: 600000 | J3: 0 | K3: =H3*I3*(1-J3/100) -> 600000
A4: S0003 | B4: 46167 | C4: Mahindra | D4: XUV700 | E4: Diesel | F4: North | G4: Elite Auto | H4: 7 | I4: 1600000 | J4: 0 | K4: =H4*I4*(1-J4/100) -> 11200000
A5: S0004 | B5: 46079 | C5: Maruti Suzuki | D5: Baleno | E5: Petrol | F5: Central | G5: Elite Auto | H5: 7 | I5: 700000 | J5: 0 | K5: =H5*I5*(1-J5/100) -> 4900000
A6: S0005 | B6: 46053 | C6: Maruti Suzuki | D6: WagonR | E6: Diesel | F6: East | G6: Speedway Motors | H6: 3 | I6: 600000 | J6: 10 | K6: =H6*I6*(1-J6/100) -> 1620000
A7: S0006 | B7: 46118 | C7: Kia | D7: Carens | E7: Diesel | F7: North | G7: Elite Auto | H7: 10 | I7: 1100000 | J7: 2 | K7: =H7*I7*(1-J7/100) -> 10780000
A8: S0007 | B8: 46150 | C8: Maruti Suzuki | D8: WagonR | E8: Petrol | F8: Central | G8: Prime Motors | H8: 10 | I8: 600000 | J8: 2 | K8: =H8*I8*(1-J8/100) -> 5880000
A9: S0008 | B9: 46115 | C9: Toyota | D9: Urban Cruiser | E9: CNG | F9: West | G9: Elite Auto | H9: 15 | I9: 900000 | J9: 7 | K9: =H9*I9*(1-J9/100) -> 12555000
A10: S0009 | B10: 46157 | C10: Tata | D10: Punch | E10: Diesel | F10: South | G10: Prime Motors | H10: 10 | I10: 700000 | J10: 5 | K10: =H10*I10*(1-J10/100) -> 6650000
A11: S0010 | B11: 46154 | C11: Mahindra | D11: Thar | E11: Electric | F11: East | G11: Elite Auto | H11: 2 | I11: 1300000 | J11: 0 | K11: =H11*I11*(1-J11/100) -> 2600000
A12: S0011 | B12: 46194 | C12: Mahindra | D12: Scorpio | E12: CNG | F12: South | G12: Speedway Motors | H12: 7 | I12: 1400000 | J12: 0 | K12: =H12*I12*(1-J12/100) -> 9800000
A13: S0012 | B13: 46171 | C13: Maruti Suzuki | D13: WagonR | E13: CNG | F13: East | G13: Metro Cars | H13: 10 | I13: 600000 | J13: 7 | K13: =H13*I13*(1-J13/100) -> 5580000
... A101: S0100 | B101: 46126 | C101: Mahindra | D101: Thar | E101: CNG | F101: East | G101: Metro Cars | H101: 12 | I101: 1300000 | J101: 5 | K101: =H101*I101*(1-J101/100) -> 14820000

Sheet Summary
B2: Monthly Revenue Trend | F2: Revenue by Brand | J2: Revenue by Region | M2: Revenue by Fuel Type
B4: Month | C4: Revenue (INR) | F4: Brand | G4: Units Sold | H4: Revenue (INR) | J4: Region | K4: Revenue (INR) | M4: Fuel Type | N4: Revenue (INR)
B5: Jan-2026 | C5: =SUMPRODUCT(('Sales Data'!$B$2:$B$101>=DATE(2026,1,1))*('Sales Data'!$B$2:$B$101<DATE(2026,2,1))*'Sales Data'!$K$2:$K$101) -> 102806500 | F5: Honda | G5: =SUMIFS('Sales Data'!$H$2:$H$101,'Sales Data'!$C$2:$C$101,F5) -> 75 | H5: =SUMIFS('Sales Data'!$K$2:$K$101,'Sales Data'!$C$2:$C$101,F5) -> 83740000 | J5: Central | K5: =SUMIFS('Sales Data'!$K$2:$K$101,'Sales Data'!$F$2:$F$101,J5) -> 172706500 | M5: CNG | N5: =SUMIFS('Sales Data'!$K$2:$K$101,'Sales Data'!$E$2:$E$101,M5) -> 196160500
B6: Feb-2026 | C6: =SUMPRODUCT(('Sales Data'!$B$2:$B$101>=DATE(2026,2,1))*('Sales Data'!$B$2:$B$101<DATE(2026,3,1))*'Sales Data'!$K$2:$K$101) -> 110533000 | F6: Hyundai | G6: =SUMIFS('Sales Data'!$H$2:$H$101,'Sales Data'!$C$2:$C$101,F6) -> 111 | H6: =SUMIFS('Sales Data'!$K$2:$K$101,'Sales Data'!$C$2:$C$101,F6) -> 99704000 | J6: East | K6: =SUMIFS('Sales Data'!$K$2:$K$101,'Sales Data'!$F$2:$F$101,J6) -> 126975500 | M6: Diesel | N6: =SUMIFS('Sales Data'!$K$2:$K$101,'Sales Data'!$E$2:$E$101,M6) -> 223107000
B7: Mar-2026 | C7: =SUMPRODUCT(('Sales Data'!$B$2:$B$101>=DATE(2026,3,1))*('Sales Data'!$B$2:$B$101<DATE(2026,4,1))*'Sales Data'!$K$2:$K$101) -> 105024000 | F7: Kia | G7: =SUMIFS('Sales Data'!$H$2:$H$101,'Sales Data'!$C$2:$C$101,F7) -> 108 | H7: =SUMIFS('Sales Data'!$K$2:$K$101,'Sales Data'!$C$2:$C$101,F7) -> 101018500 | J7: North | K7: =SUMIFS('Sales Data'!$K$2:$K$101,'Sales Data'!$F$2:$F$101,J7) -> 154454500 | M7: Electric | N7: =SUMIFS('Sales Data'!$K$2:$K$101,'Sales Data'!$E$2:$E$101,M7) -> 143313000
B8: Apr-2026 | C8: =SUMPRODUCT(('Sales Data'!$B$2:$B$101>=DATE(2026,4,1))*('Sales Data'!$B$2:$B$101<DATE(2026,5,1))*'Sales Data'!$K$2:$K$101) -> 157046000 | F8: Mahindra | G8: =SUMIFS('Sales Data'!$H$2:$H$101,'Sales Data'!$C$2:$C$101,F8) -> 110 | H8: =SUMIFS('Sales Data'!$K$2:$K$101,'Sales Data'!$C$2:$C$101,F8) -> 136538500 | J8: South | K8: =SUMIFS('Sales Data'!$K$2:$K$101,'Sales Data'!$F$2:$F$101,J8) -> 119157000 | M8: Petrol | N8: =SUMIFS('Sales Data'!$K$2:$K$101,'Sales Data'!$E$2:$E$101,M8) -> 165371500
B9: May-2026 | C9: =SUMPRODUCT(('Sales Data'!$B$2:$B$101>=DATE(2026,5,1))*('Sales Data'!$B$2:$B$101<DATE(2026,6,1))*'Sales Data'!$K$2:$K$101) -> 137527500 | F9: Maruti Suzuki | G9: =SUMIFS('Sales Data'!$H$2:$H$101,'Sales Data'!$C$2:$C$101,F9) -> 157 | H9: =SUMIFS('Sales Data'!$K$2:$K$101,'Sales Data'!$C$2:$C$101,F9) -> 101079000 | J9: West | K9: =SUMIFS('Sales Data'!$K$2:$K$101,'Sales Data'!$F$2:$F$101,J9) -> 154658500
B10: Jun-2026 | C10: =SUMPRODUCT(('Sales Data'!$B$2:$B$101>=DATE(2026,6,1))*('Sales Data'!$B$2:$B$101<DATE(2026,7,1))*'Sales Data'!$K$2:$K$101) -> 19984000 | F10: Tata | G10: =SUMIFS('Sales Data'!$H$2:$H$101,'Sales Data'!$C$2:$C$101,F10) -> 95 | H10: =SUMIFS('Sales Data'!$K$2:$K$101,'Sales Data'!$C$2:$C$101,F10) -> 79939000
B11: Jul-2026 | C11: =SUMPRODUCT(('Sales Data'!$B$2:$B$101>=DATE(2026,7,1))*('Sales Data'!$B$2:$B$101<DATE(2026,8,1))*'Sales Data'!$K$2:$K$101) -> 95031000 | F11: Toyota | G11: =SUMIFS('Sales Data'!$H$2:$H$101,'Sales Data'!$C$2:$C$101,F11) -> 107 | H11: =SUMIFS('Sales Data'!$K$2:$K$101,'Sales Data'!$C$2:$C$101,F11) -> 125933000
